{
    "HPDelta": "HP_FLAT",
    "HPAddedRatio": "HP_PERCENT",
    "DefenceDelta": "DEF_FLAT",
    "DefenceAddedRatio": "DEF_PERCENT",
    "AttackDelta": "ATK_FLAT",
    "AttackAddedRatio": "ATK_PERCENT",
    "SpeedDelta": "SPEED_FLAT",
    "CriticalChance": "CRIT_CHANCE",
    "CriticalDamage": "CRIT_DMG",
    "CriticalChanceBase": "CRIT_CHANCE",
    "CriticalDamageBase": "CRIT_DMG",
    "SPRatioBase": "ENERGY_REGEN",
    "StatusProbability": "EFFECT_HIT_RATE",
    "StatusResistance": "EFFECT_RES",
    "HealRatioBase": "HEAL_BOOST",
    "BreakDamageAddedRatio": "BREAK_EFFECT",
    "FireAddedRatio": "FIRE_DMG_PERCENT",
    "IceAddedRatio": "ICE_DMG_PERCENT",
    "ThunderAddedRatio": "THUNDER_DMG_PERCENT",
    "QuantumAddedRatio": "QUANTUM_DMG_PERCENT",
    "ImaginaryAddedRatio": "IMAGINARY_DMG_PERCENT",
    "WindAddedRatio": "WIND_DMG_PERCENT",
    "PhysicalAddedRatio": "PHYSICAL_DMG_PERCENT"
}